{
  "contact": [
    {
      "title": "fly",
      "items": [
        {
          "name": "Dewi",
          "phone": "6281283215788"
        },
        {
          "name": "Ferdi",
          "phone": "6282317188008"
        },
        {
          "name": "Tami",
          "phone": "6285365200800"
        },
        {
          "name": "Jennifer",
          "phone": "6282365558008"
        },
        {
          "name": "Egita",
          "phone": "6285207888008"
        },
        {
          "name": "Desi",
          "phone": "6285297488822"
        },
        {
          "name": "Dini",
          "phone": "6282129904869"
        },
        {
          "name": "Adnan",
          "phone": "6281228886940"
        },
        {
          "name": "Ronav",
          "phone": "6282295675189"
        } 
      ]
    },
    {
      "title": "stay",
      "items": [
        {
          "name": "Catherine",
          "phone": "6287869010988"
        },
        {
          "name": "Yuni",
          "phone": "6282137103774"
        },
        {
          "name": "Efendi",
          "phone": "6285207888833"
        },
        {
          "name": "Ika",
          "phone": "6282211121231"
        },
        {
          "name": "Richard",
          "phone": "6282298877800"
        }
      ]
    },
    {
      "title": "docs",
      "items": [
        {
          "name": "Hengki",
          "phone": "6285218418647"
        },
        {
          "name": "Ima",
          "phone": "6281283210688"
        },
        {
          "name": "Wendy",
          "phone": "6282320008886"
        },
        {
          "name": "Wisda",
          "phone": "6281257571231"
        },
        {
          "name": "Tubagus (Jakarta)",
          "phone": "6287761706656"
        }
        
      ]
    },
    {
      "title": "tour",
      "items": [
        {
          "name": "Dennis",
          "phone": "6285297580000"
        },
        {
          "name": "Louis",
          "phone": "628811906396"
        },
        {
          "name": "Marvin",
          "phone": "6285827879667"
        },
        {
          "name": "Nicholas",
          "phone": "6285207888877"
        }
      ]
    },
    {
      "title": "play",
      "items": [
        {
          "name": "Felix",
          "phone": "6285207888188"
        },
        {
          "name": "Sendy",
          "phone": "6282315139543"
        }
      ]
    },
    {
      "title": "B2B & Corporate",
      "items": [
        {
          "name": "Denny Kurniawan",
          "phone": "628818128661"
        }
      ]
    }
  ]
}
